{
  "title": "naget",
  "language": "en",
  "description": "Most recent changes with links to updates",
  "link": "",
  "items": [
    {
      "title": "naget 1.0.0-alpha.1",
      "version": "1.0.0-alpha.1",
      "short_version": "1.0.0",
      "description": "",
      "url": "https://github.com/Milkeyyy/naget/releases/download/1.0.0-alpha.1/naget_Setup_win-arm64.exe",
      "signature": "wAXb8OIfguBqwWCPdcrLbsrFmz08DjWHaXq3pGmEF8j572TLzAGHAdN7ytd6TmGRiBM7VNoURMO5p/wFLvbKBw==",
      "publication_date": "2025-07-30T18:03:09.8124975Z",
      "is_critical": false,
      "size": 129866005,
      "os": "windows-arm64",
      "channel": "alpha",
      "type": "application/x-msdos-program"
    }
  ]
}